danbi/__init__.py
danbi/database/ConnMngPsql.py
danbi/database/ConnMngPsqlAsync.py
danbi/database/ConnMngSqlite.py
danbi/database/DBPsql.py
danbi/database/DBPsqlAsync.py
danbi/database/DBSqlite.py
danbi/database/IConnectionManager.py
danbi/database/IDB.py
danbi/database/__init__.py
danbi/database/factory.py
danbi/dataprocess/DataBalance.py
danbi/dataprocess/GroupCorrelation.py
danbi/dataprocess/TimeseriesToImage.py
danbi/dataprocess/ZeroBaseMinMaxScaler.py
danbi/dataprocess/__init__.py
danbi/dataprocess/analysis.py
danbi/dataprocess/convert.py
danbi/dataprocess/signal.py
danbi/extends/__init__.py
danbi/extends/bibokeh/__init__.py
danbi/extends/bibokeh/plot_chart.py
danbi/extends/bibokeh/show.py
danbi/extends/bipandas/__init__.py
danbi/extends/bipandas/column_ext.py
danbi/extends/bipandas/dataframe_ext.py
danbi/extends/bipandas/state.py
danbi/extends/biray/__init__.py
danbi/extends/biray/ray.py
danbi/extends/bitensorflow/__init__.py
danbi/extends/bitensorflow/layers/FeatureMasking.py
danbi/extends/bitensorflow/layers/__init__.py
danbi/extends/bitensorflow/tfrecord_ext.py
danbi/extends/bitensorflow/visualization.py
danbi/mapping/IMapper.py
danbi/mapping/Jinja2Mapper.py
danbi/mapping/YAMLConfig.py
danbi/mapping/__init__.py
danbi/plugable/IPlugin.py
danbi/plugable/IPluginAsync.py
danbi/plugable/PluginManager.py
danbi/plugable/__init__.py
danbi/utils/DotDict.py
danbi/utils/EduPlot.py
danbi/utils/__init__.py
danbi/utils/day_time.py
danbi/utils/info.py
danbi/utils/jupyter.py
danbi/utils/util.py
danbi/utils/with_print.py
danbi-0.3.33.dist-info/LICENSE
danbi-0.3.33.dist-info/METADATA
danbi-0.3.33.dist-info/WHEEL
danbi-0.3.33.dist-info/RECORD
